<annotation>
	<folder>JPEGImages</folder>
	<filename>001551.jpg</filename>
	<path>C:\Users\Lenovo\Desktop\VOC2007\JPEGImages\001551.jpg</path>
	<source>
		<database>Unknown</database>
	</source>
	<size>
		<width>640</width>
		<height>480</height>
		<depth>3</depth>
	</size>
	<segmented>0</segmented>
	<object>
		<name>deflection</name>
		<pose>Unspecified</pose>
		<truncated>0</truncated>
		<difficult>0</difficult>
		<bndbox>
			<xmin>219</xmin>
			<ymin>78</ymin>
			<xmax>288</xmax>
			<ymax>161</ymax>
		</bndbox>
	</object>
	<object>
		<name>person</name>
		<pose>Unspecified</pose>
		<truncated>0</truncated>
		<difficult>0</difficult>
		<bndbox>
			<xmin>211</xmin>
			<ymin>141</ymin>
			<xmax>300</xmax>
			<ymax>357</ymax>
		</bndbox>
	</object>
</annotation>
